ormlite/__init__.py
ormlite/adapters.py
ormlite/errors.py
ormlite/migrate.py
ormlite/orm.py
ormlite/query.py
ormlite/sqlite.py
ormlite/utils.py
ormlite-0.2.1.dist-info/LICENSE
ormlite-0.2.1.dist-info/METADATA
ormlite-0.2.1.dist-info/WHEEL
ormlite-0.2.1.dist-info/top_level.txt
ormlite-0.2.1.dist-info/RECORD
