Metadata-Version: 2.1
Name: ormlite
Version: 0.2.1
Summary: Two way binding from Python Dataclasses to Sqlite tables
Author-email: Charles Taylor <charlestaylor95@gmail.com>
License: Copyright 2023 Charles Taylor
Project-URL: Github Repo, https://github.com/CharlesTaylor7/ormlite
Project-URL: Read The Docs, https://ormlite.readthedocs.io/en/latest/
Keywords: sqlite,orm,dataclass,data,query,migration
Classifier: Development Status :: 3 - Alpha
Classifier: Programming Language :: Python :: 3
Classifier: Programming Language :: Python :: 3.11
Requires-Python: >=3.11
License-File: LICENSE
Provides-Extra: dev
Requires-Dist: black ; extra == 'dev'
Requires-Dist: pytest ; extra == 'dev'
Requires-Dist: pytest-cov ; extra == 'dev'
Requires-Dist: sphinx ; extra == 'dev'
Requires-Dist: myst-parser ; extra == 'dev'
